openai_python_mocks/__init__.py
openai_python_mocks-0.0.1.dist-info/LICENSE
openai_python_mocks-0.0.1.dist-info/METADATA
openai_python_mocks-0.0.1.dist-info/WHEEL
openai_python_mocks-0.0.1.dist-info/RECORD
