Metadata-Version: 2.1
Name: openai-python-mocks
Version: 0.0.1
Summary: 
Author: Daria Neznaeva
Author-email: darianeznaeva@gmail.com
Requires-Python: >=3.9,<4.0
Classifier: Programming Language :: Python :: 3
Classifier: Programming Language :: Python :: 3.9
Classifier: Programming Language :: Python :: 3.10
Classifier: Programming Language :: Python :: 3.11
Requires-Dist: decorator (>=5.1.1,<6.0.0)
Requires-Dist: openai (>=0.27.4,<0.28.0)
Requires-Dist: responses (>=0.23.1,<0.24.0)
